{
  "version": 2,
  "name": "lightning-reader",
  "alias": "lightningreader.club",
  "build": {
    "env": {
      "SESSION_SECRET": "@session-secret",
      "OPEN_NODE_KEY": "@open-node-key",
      "APP_PRIVATE_KEY": "@app-private-key"
    }
  },
  "builds": [
    {
      "src": "api/**/*.js",
      "use": "@now/node"
    },
    {
      "src": "package.json",
      "use": "@now/static-build",
      "config": {
        "distDir": "public/build"
      }
    }
  ],
  "routes": [
    { "src": "/(.*).((woff?2)|(tiff)|(eot))", "dest": "" },
    { "src": "/favicon.ico", "dest": "/favicon.ico" },
    { "src": "/asset-manifest.json", "dest": "/asset-manifest.json" },
    { "src": "/manifest.json", "dest": "/manifest.json" },
    { "src": "/precache-manifest.(.*)", "dest": "/precache-manifest.$1" },
    {
      "src": "/api/docs/(.*)",
      "dest": "/api/docs"
    },
    {
      "src": "/api/node/(.*)",
      "dest": "/api/node"
    },
    {
      "src": "/api/radiks/(.*)",
      "dest": "/api/radiks"
    },
    {
      "src": "/api/invoice(.*)",
      "dest": "/api/invoice"
    }
  ]
}
